{
    "uid": "7eaa40a9-cb24-4492-b4c1-a6595f6e326b",
    "name": "32_RandomForest",
    "preprocessing": [
        {
            "missing_values": [
                {
                    "fill_method": "na_fill_median",
                    "fill_params": {
                        "BREADTH": 0.39999999999999997,
                        "DEPTH": 0.6666666666666666,
                        "DRAUGHT": 0.5,
                        "LENGTH": 0.4473684210526316,
                        "VOLUME": 0.15833333333333335
                    },
                    "datetime_columns": []
                }
            ],
            "scale_y": {
                "scale": [
                    171.27907720759387
                ],
                "mean": [
                    62.09814334400999
                ],
                "var": [
                    29336.522289084904
                ],
                "n_samples_seen": 352745,
                "n_features_in": 1,
                "columns": [
                    "target"
                ],
                "scale_method": "scale_normal"
            },
            "ml_task": "regression",
            "params": {
                "columns_preprocessing": {
                    "BREADTH": [
                        "na_fill_median"
                    ],
                    "DEPTH": [
                        "na_fill_median"
                    ],
                    "DRAUGHT": [
                        "na_fill_median"
                    ],
                    "LENGTH": [
                        "na_fill_median"
                    ],
                    "VOLUME": [
                        "na_fill_median"
                    ]
                },
                "target_preprocessing": [
                    "na_exclude",
                    "scale_normal"
                ],
                "ml_task": "regression"
            }
        },
        {
            "missing_values": [
                {
                    "fill_method": "na_fill_median",
                    "fill_params": {
                        "BREADTH": 0.39999999999999997,
                        "DEPTH": 0.6666666666666666,
                        "DRAUGHT": 0.5,
                        "LENGTH": 0.4473684210526316,
                        "VOLUME": 0.15833333333333335
                    },
                    "datetime_columns": []
                }
            ],
            "scale_y": {
                "scale": [
                    170.9048066853953
                ],
                "mean": [
                    61.99568631491855
                ],
                "var": [
                    29208.452948172337
                ],
                "n_samples_seen": 352745,
                "n_features_in": 1,
                "columns": [
                    "target"
                ],
                "scale_method": "scale_normal"
            },
            "ml_task": "regression",
            "params": {
                "columns_preprocessing": {
                    "BREADTH": [
                        "na_fill_median"
                    ],
                    "DEPTH": [
                        "na_fill_median"
                    ],
                    "DRAUGHT": [
                        "na_fill_median"
                    ],
                    "LENGTH": [
                        "na_fill_median"
                    ],
                    "VOLUME": [
                        "na_fill_median"
                    ]
                },
                "target_preprocessing": [
                    "na_exclude",
                    "scale_normal"
                ],
                "ml_task": "regression"
            }
        },
        {
            "missing_values": [
                {
                    "fill_method": "na_fill_median",
                    "fill_params": {
                        "BREADTH": 0.39999999999999997,
                        "DEPTH": 0.6666666666666666,
                        "DRAUGHT": 0.5,
                        "LENGTH": 0.4473684210526316,
                        "VOLUME": 0.15833333333333335
                    },
                    "datetime_columns": []
                }
            ],
            "scale_y": {
                "scale": [
                    170.85589657080092
                ],
                "mean": [
                    61.906523205272066
                ],
                "var": [
                    29191.737393012223
                ],
                "n_samples_seen": 352745,
                "n_features_in": 1,
                "columns": [
                    "target"
                ],
                "scale_method": "scale_normal"
            },
            "ml_task": "regression",
            "params": {
                "columns_preprocessing": {
                    "BREADTH": [
                        "na_fill_median"
                    ],
                    "DEPTH": [
                        "na_fill_median"
                    ],
                    "DRAUGHT": [
                        "na_fill_median"
                    ],
                    "LENGTH": [
                        "na_fill_median"
                    ],
                    "VOLUME": [
                        "na_fill_median"
                    ]
                },
                "target_preprocessing": [
                    "na_exclude",
                    "scale_normal"
                ],
                "ml_task": "regression"
            }
        },
        {
            "missing_values": [
                {
                    "fill_method": "na_fill_median",
                    "fill_params": {
                        "BREADTH": 0.39999999999999997,
                        "DEPTH": 0.6666666666666666,
                        "DRAUGHT": 0.5,
                        "LENGTH": 0.4473684210526316,
                        "VOLUME": 0.15833333333333335
                    },
                    "datetime_columns": []
                }
            ],
            "scale_y": {
                "scale": [
                    170.5663872170725
                ],
                "mean": [
                    61.83419108540216
                ],
                "var": [
                    29092.89244828431
                ],
                "n_samples_seen": 352745,
                "n_features_in": 1,
                "columns": [
                    "target"
                ],
                "scale_method": "scale_normal"
            },
            "ml_task": "regression",
            "params": {
                "columns_preprocessing": {
                    "BREADTH": [
                        "na_fill_median"
                    ],
                    "DEPTH": [
                        "na_fill_median"
                    ],
                    "DRAUGHT": [
                        "na_fill_median"
                    ],
                    "LENGTH": [
                        "na_fill_median"
                    ],
                    "VOLUME": [
                        "na_fill_median"
                    ]
                },
                "target_preprocessing": [
                    "na_exclude",
                    "scale_normal"
                ],
                "ml_task": "regression"
            }
        },
        {
            "scale_y": {
                "scale": [
                    170.400599691492
                ],
                "mean": [
                    61.769999203841
                ],
                "var": [
                    29036.36437522011
                ],
                "n_samples_seen": 352745,
                "n_features_in": 1,
                "columns": [
                    "target"
                ],
                "scale_method": "scale_normal"
            },
            "ml_task": "regression",
            "params": {
                "columns_preprocessing": {
                    "BREADTH": [
                        "na_fill_median"
                    ],
                    "DEPTH": [
                        "na_fill_median"
                    ],
                    "DRAUGHT": [
                        "na_fill_median"
                    ],
                    "LENGTH": [
                        "na_fill_median"
                    ],
                    "VOLUME": [
                        "na_fill_median"
                    ]
                },
                "target_preprocessing": [
                    "na_exclude",
                    "scale_normal"
                ],
                "ml_task": "regression"
            }
        },
        {
            "missing_values": [
                {
                    "fill_method": "na_fill_median",
                    "fill_params": {
                        "BREADTH": 0.39999999999999997,
                        "DEPTH": 0.6666666666666666,
                        "DRAUGHT": 0.5,
                        "LENGTH": 0.4473684210526316,
                        "VOLUME": 0.15833333333333335
                    },
                    "datetime_columns": []
                }
            ],
            "scale_y": {
                "scale": [
                    170.62501577456538
                ],
                "mean": [
                    61.85969625204712
                ],
                "var": [
                    29112.896008070686
                ],
                "n_samples_seen": 352745,
                "n_features_in": 1,
                "columns": [
                    "target"
                ],
                "scale_method": "scale_normal"
            },
            "ml_task": "regression",
            "params": {
                "columns_preprocessing": {
                    "BREADTH": [
                        "na_fill_median"
                    ],
                    "DEPTH": [
                        "na_fill_median"
                    ],
                    "DRAUGHT": [
                        "na_fill_median"
                    ],
                    "LENGTH": [
                        "na_fill_median"
                    ],
                    "VOLUME": [
                        "na_fill_median"
                    ]
                },
                "target_preprocessing": [
                    "na_exclude",
                    "scale_normal"
                ],
                "ml_task": "regression"
            }
        },
        {
            "missing_values": [
                {
                    "fill_method": "na_fill_median",
                    "fill_params": {
                        "BREADTH": 0.39999999999999997,
                        "DEPTH": 0.6666666666666666,
                        "DRAUGHT": 0.5,
                        "LENGTH": 0.4473684210526316,
                        "VOLUME": 0.15833333333333335
                    },
                    "datetime_columns": []
                }
            ],
            "scale_y": {
                "scale": [
                    171.1023458437324
                ],
                "mean": [
                    62.00549251181623
                ],
                "var": [
                    29276.012753228206
                ],
                "n_samples_seen": 352745,
                "n_features_in": 1,
                "columns": [
                    "target"
                ],
                "scale_method": "scale_normal"
            },
            "ml_task": "regression",
            "params": {
                "columns_preprocessing": {
                    "BREADTH": [
                        "na_fill_median"
                    ],
                    "DEPTH": [
                        "na_fill_median"
                    ],
                    "DRAUGHT": [
                        "na_fill_median"
                    ],
                    "LENGTH": [
                        "na_fill_median"
                    ],
                    "VOLUME": [
                        "na_fill_median"
                    ]
                },
                "target_preprocessing": [
                    "na_exclude",
                    "scale_normal"
                ],
                "ml_task": "regression"
            }
        },
        {
            "missing_values": [
                {
                    "fill_method": "na_fill_median",
                    "fill_params": {
                        "BREADTH": 0.39999999999999997,
                        "DEPTH": 0.6666666666666666,
                        "DRAUGHT": 0.5,
                        "LENGTH": 0.4473684210526316,
                        "VOLUME": 0.15833333333333335
                    },
                    "datetime_columns": []
                }
            ],
            "scale_y": {
                "scale": [
                    170.9026705904257
                ],
                "mean": [
                    61.97379235392186
                ],
                "var": [
                    29207.722814939567
                ],
                "n_samples_seen": 352745,
                "n_features_in": 1,
                "columns": [
                    "target"
                ],
                "scale_method": "scale_normal"
            },
            "ml_task": "regression",
            "params": {
                "columns_preprocessing": {
                    "BREADTH": [
                        "na_fill_median"
                    ],
                    "DEPTH": [
                        "na_fill_median"
                    ],
                    "DRAUGHT": [
                        "na_fill_median"
                    ],
                    "LENGTH": [
                        "na_fill_median"
                    ],
                    "VOLUME": [
                        "na_fill_median"
                    ]
                },
                "target_preprocessing": [
                    "na_exclude",
                    "scale_normal"
                ],
                "ml_task": "regression"
            }
        },
        {
            "missing_values": [
                {
                    "fill_method": "na_fill_median",
                    "fill_params": {
                        "BREADTH": 0.39999999999999997,
                        "DEPTH": 0.6666666666666666,
                        "DRAUGHT": 0.5,
                        "LENGTH": 0.4473684210526316,
                        "VOLUME": 0.15833333333333335
                    },
                    "datetime_columns": []
                }
            ],
            "scale_y": {
                "scale": [
                    170.8951149593121
                ],
                "mean": [
                    62.03929477853114
                ],
                "var": [
                    29205.140316956506
                ],
                "n_samples_seen": 352745,
                "n_features_in": 1,
                "columns": [
                    "target"
                ],
                "scale_method": "scale_normal"
            },
            "ml_task": "regression",
            "params": {
                "columns_preprocessing": {
                    "BREADTH": [
                        "na_fill_median"
                    ],
                    "DEPTH": [
                        "na_fill_median"
                    ],
                    "DRAUGHT": [
                        "na_fill_median"
                    ],
                    "LENGTH": [
                        "na_fill_median"
                    ],
                    "VOLUME": [
                        "na_fill_median"
                    ]
                },
                "target_preprocessing": [
                    "na_exclude",
                    "scale_normal"
                ],
                "ml_task": "regression"
            }
        },
        {
            "missing_values": [
                {
                    "fill_method": "na_fill_median",
                    "fill_params": {
                        "BREADTH": 0.39999999999999997,
                        "DEPTH": 0.6666666666666666,
                        "DRAUGHT": 0.5,
                        "LENGTH": 0.4473684210526316,
                        "VOLUME": 0.15833333333333335
                    },
                    "datetime_columns": []
                }
            ],
            "scale_y": {
                "scale": [
                    170.5592947106472
                ],
                "mean": [
                    61.92552692066284
                ],
                "var": [
                    29090.473012193408
                ],
                "n_samples_seen": 352746,
                "n_features_in": 1,
                "columns": [
                    "target"
                ],
                "scale_method": "scale_normal"
            },
            "ml_task": "regression",
            "params": {
                "columns_preprocessing": {
                    "BREADTH": [
                        "na_fill_median"
                    ],
                    "DEPTH": [
                        "na_fill_median"
                    ],
                    "DRAUGHT": [
                        "na_fill_median"
                    ],
                    "LENGTH": [
                        "na_fill_median"
                    ],
                    "VOLUME": [
                        "na_fill_median"
                    ]
                },
                "target_preprocessing": [
                    "na_exclude",
                    "scale_normal"
                ],
                "ml_task": "regression"
            }
        }
    ],
    "learners": [
        {
            "library_version": "1.4.1.post1",
            "algorithm_name": "Random Forest",
            "algorithm_short_name": "Random Forest",
            "uid": "6a0e1e82-c23a-49a7-a97e-9a2f9765d44f",
            "params": {
                "model_type": "Random Forest",
                "ml_task": "regression",
                "n_jobs": -1,
                "seed": 43,
                "criterion": "squared_error",
                "max_features": 1.0,
                "min_samples_split": 40,
                "max_depth": 4,
                "eval_metric_name": "mae",
                "explain_level": 0
            },
            "name": "learner_fold_0"
        },
        {
            "library_version": "1.4.1.post1",
            "algorithm_name": "Random Forest",
            "algorithm_short_name": "Random Forest",
            "uid": "bc977c90-d9b2-4353-9653-4196444445d5",
            "params": {
                "model_type": "Random Forest",
                "ml_task": "regression",
                "n_jobs": -1,
                "seed": 43,
                "criterion": "squared_error",
                "max_features": 1.0,
                "min_samples_split": 40,
                "max_depth": 4,
                "eval_metric_name": "mae",
                "explain_level": 0
            },
            "name": "learner_fold_1"
        },
        {
            "library_version": "1.4.1.post1",
            "algorithm_name": "Random Forest",
            "algorithm_short_name": "Random Forest",
            "uid": "a2c2fcb5-a8d3-4243-9e50-02e13e1fa279",
            "params": {
                "model_type": "Random Forest",
                "ml_task": "regression",
                "n_jobs": -1,
                "seed": 43,
                "criterion": "squared_error",
                "max_features": 1.0,
                "min_samples_split": 40,
                "max_depth": 4,
                "eval_metric_name": "mae",
                "explain_level": 0
            },
            "name": "learner_fold_2"
        },
        {
            "library_version": "1.4.1.post1",
            "algorithm_name": "Random Forest",
            "algorithm_short_name": "Random Forest",
            "uid": "6ed6656e-04f7-417c-ae59-325a7a512422",
            "params": {
                "model_type": "Random Forest",
                "ml_task": "regression",
                "n_jobs": -1,
                "seed": 43,
                "criterion": "squared_error",
                "max_features": 1.0,
                "min_samples_split": 40,
                "max_depth": 4,
                "eval_metric_name": "mae",
                "explain_level": 0
            },
            "name": "learner_fold_3"
        },
        {
            "library_version": "1.4.1.post1",
            "algorithm_name": "Random Forest",
            "algorithm_short_name": "Random Forest",
            "uid": "cfcee52e-d7d6-4493-a923-39bdd4c89b22",
            "params": {
                "model_type": "Random Forest",
                "ml_task": "regression",
                "n_jobs": -1,
                "seed": 43,
                "criterion": "squared_error",
                "max_features": 1.0,
                "min_samples_split": 40,
                "max_depth": 4,
                "eval_metric_name": "mae",
                "explain_level": 0
            },
            "name": "learner_fold_4"
        },
        {
            "library_version": "1.4.1.post1",
            "algorithm_name": "Random Forest",
            "algorithm_short_name": "Random Forest",
            "uid": "58a7f838-e8bb-4f35-a131-a64aaa871261",
            "params": {
                "model_type": "Random Forest",
                "ml_task": "regression",
                "n_jobs": -1,
                "seed": 43,
                "criterion": "squared_error",
                "max_features": 1.0,
                "min_samples_split": 40,
                "max_depth": 4,
                "eval_metric_name": "mae",
                "explain_level": 0
            },
            "name": "learner_fold_5"
        },
        {
            "library_version": "1.4.1.post1",
            "algorithm_name": "Random Forest",
            "algorithm_short_name": "Random Forest",
            "uid": "d4877bea-5b6f-46ee-b2d8-b3e9fcb1f699",
            "params": {
                "model_type": "Random Forest",
                "ml_task": "regression",
                "n_jobs": -1,
                "seed": 43,
                "criterion": "squared_error",
                "max_features": 1.0,
                "min_samples_split": 40,
                "max_depth": 4,
                "eval_metric_name": "mae",
                "explain_level": 0
            },
            "name": "learner_fold_6"
        },
        {
            "library_version": "1.4.1.post1",
            "algorithm_name": "Random Forest",
            "algorithm_short_name": "Random Forest",
            "uid": "9ef716b5-c46e-4569-ad47-afce397162d3",
            "params": {
                "model_type": "Random Forest",
                "ml_task": "regression",
                "n_jobs": -1,
                "seed": 43,
                "criterion": "squared_error",
                "max_features": 1.0,
                "min_samples_split": 40,
                "max_depth": 4,
                "eval_metric_name": "mae",
                "explain_level": 0
            },
            "name": "learner_fold_7"
        },
        {
            "library_version": "1.4.1.post1",
            "algorithm_name": "Random Forest",
            "algorithm_short_name": "Random Forest",
            "uid": "d6da42e4-e115-4e0e-b474-85a1dc600122",
            "params": {
                "model_type": "Random Forest",
                "ml_task": "regression",
                "n_jobs": -1,
                "seed": 43,
                "criterion": "squared_error",
                "max_features": 1.0,
                "min_samples_split": 40,
                "max_depth": 4,
                "eval_metric_name": "mae",
                "explain_level": 0
            },
            "name": "learner_fold_8"
        },
        {
            "library_version": "1.4.1.post1",
            "algorithm_name": "Random Forest",
            "algorithm_short_name": "Random Forest",
            "uid": "5c39af38-d250-400d-a1b0-72a7f218038e",
            "params": {
                "model_type": "Random Forest",
                "ml_task": "regression",
                "n_jobs": -1,
                "seed": 43,
                "criterion": "squared_error",
                "max_features": 1.0,
                "min_samples_split": 40,
                "max_depth": 4,
                "eval_metric_name": "mae",
                "explain_level": 0
            },
            "name": "learner_fold_9"
        }
    ],
    "params": {
        "additional": {
            "trees_in_step": 100,
            "train_cant_improve_limit": 1,
            "min_steps": 1,
            "max_steps": 50,
            "early_stopping_rounds": 50,
            "max_rows_limit": null,
            "max_cols_limit": null
        },
        "preprocessing": {
            "columns_preprocessing": {
                "BREADTH": [
                    "na_fill_median"
                ],
                "DEPTH": [
                    "na_fill_median"
                ],
                "DRAUGHT": [
                    "na_fill_median"
                ],
                "LENGTH": [
                    "na_fill_median"
                ],
                "VOLUME": [
                    "na_fill_median"
                ]
            },
            "target_preprocessing": [
                "na_exclude",
                "scale_normal"
            ],
            "ml_task": "regression"
        },
        "validation_strategy": {
            "validation_type": "kfold",
            "k_folds": 10,
            "shuffle": true,
            "X_path": "AutoML_2\\X.data",
            "y_path": "AutoML_2\\y.data",
            "results_path": "AutoML_2"
        },
        "learner": {
            "model_type": "Random Forest",
            "ml_task": "regression",
            "n_jobs": -1,
            "seed": 43,
            "criterion": "squared_error",
            "max_features": 1.0,
            "min_samples_split": 40,
            "max_depth": 4,
            "eval_metric_name": "mae",
            "explain_level": 0
        },
        "automl_random_state": 42,
        "ml_task": "regression",
        "explain_level": 0,
        "name": "32_RandomForest",
        "status": "initialized",
        "final_loss": null,
        "train_time": null,
        "data_type": "original",
        "max_time_for_learner": 3600
    },
    "saved": [
        "32_RandomForest\\learner_fold_0.random_forest",
        "32_RandomForest\\learner_fold_1.random_forest",
        "32_RandomForest\\learner_fold_2.random_forest",
        "32_RandomForest\\learner_fold_3.random_forest",
        "32_RandomForest\\learner_fold_4.random_forest",
        "32_RandomForest\\learner_fold_5.random_forest",
        "32_RandomForest\\learner_fold_6.random_forest",
        "32_RandomForest\\learner_fold_7.random_forest",
        "32_RandomForest\\learner_fold_8.random_forest",
        "32_RandomForest\\learner_fold_9.random_forest"
    ],
    "predictions_fname": "32_RandomForest\\predictions_out_of_folds.csv",
    "metric_name": "mae",
    "final_loss": "62.15528982019192",
    "train_time": 459.31320548057556,
    "is_stacked": false,
    "joblib_version": "1.2.0"
}